setup.py
sanic_brotli/__init__.py
sanic_brotli_linkin.egg-info/PKG-INFO
sanic_brotli_linkin.egg-info/SOURCES.txt
sanic_brotli_linkin.egg-info/dependency_links.txt
sanic_brotli_linkin.egg-info/top_level.txt