Metadata-Version: 2.1
Name: sanic-brotli-linkin
Version: 1.0.5
Summary: Brotli Compression ALg. on Sanic responses.
Home-page: https://github.com/01ly/sanic_brotli
Author: linkin
Author-email: crawler@88.com
License: UNKNOWN
Platform: UNKNOWN
Classifier: Programming Language :: Python :: 3
Classifier: License :: OSI Approved :: MIT License
Classifier: Operating System :: OS Independent
Requires-Python: >=3.5
